example/__init__.py
example/demo.py
flask_mysql_html/__init__.py
flask_mysql_html/templates/demos.html
Flask_Mysql_Html-1.0.2.dist-info/LICENSE.txt
Flask_Mysql_Html-1.0.2.dist-info/METADATA
Flask_Mysql_Html-1.0.2.dist-info/WHEEL
Flask_Mysql_Html-1.0.2.dist-info/top_level.txt
Flask_Mysql_Html-1.0.2.dist-info/RECORD
